Pdf2TextLibrary/__init__.py
robotframework_pdf2textlibrary-1.0.1.dist-info/METADATA
robotframework_pdf2textlibrary-1.0.1.dist-info/WHEEL
robotframework_pdf2textlibrary-1.0.1.dist-info/top_level.txt
robotframework_pdf2textlibrary-1.0.1.dist-info/RECORD
