Metadata-Version: 2.1
Name: robotframework-pdf2textlibrary
Version: 1.0.1
Summary: Robot Framework PDF Inspect Library
Home-page: https://github.com/qahive/robotframework-pdf2textlibrary
Author: QA Hive Co.,Ltd
Author-email: support@qahive.com
License: Apache License 2.0
Keywords: robotframework read pdf reports
Platform: any
Classifier: Programming Language :: Python :: 3
Classifier: Programming Language :: Python :: 3.6
Classifier: Programming Language :: Python :: 3.7
Classifier: Topic :: Software Development :: Testing
Classifier: Framework :: Robot Framework
Requires-Dist: robotframework
Requires-Dist: pdfminer2
Requires-Dist: chardet
